swapy/__init__.py
swapy/middlewares.py
swapy/request.py
swapy/test.py
swapy-0.1.dist-info/DESCRIPTION.rst
swapy-0.1.dist-info/METADATA
swapy-0.1.dist-info/RECORD
swapy-0.1.dist-info/WHEEL
swapy-0.1.dist-info/metadata.json
swapy-0.1.dist-info/top_level.txt
