Metadata-Version: 2.0
Name: swapy
Version: 0.1
Summary: Easy and modular web development
Home-page: https://github.com/danieldaeschle/swapy
Author: Daniel Däschle
Author-email: daniel.daeschle@gmail.com
License: UNKNOWN
Platform: UNKNOWN
Requires-Dist: werkzeug
